ssl_checkup/__init__.py
ssl_checkup/__main__.py
ssl_checkup/cli.py
ssl_checkup/connection.py
ssl_checkup/display.py
ssl_checkup/exceptions.py
ssl_checkup/formatting.py
ssl_checkup/main.py
ssl_checkup/parser.py
ssl_checkup-1.0.2.dist-info/licenses/LICENSE
ssl_checkup-1.0.2.dist-info/METADATA
ssl_checkup-1.0.2.dist-info/WHEEL
ssl_checkup-1.0.2.dist-info/entry_points.txt
ssl_checkup-1.0.2.dist-info/top_level.txt
ssl_checkup-1.0.2.dist-info/RECORD
