Metadata-Version: 2.4
Name: ssl-checkup
Version: 1.0.2
Summary: A robust, user-friendly Python CLI tool for inspecting SSL/TLS certificates of remote servers.
Author: BaDxKaRMa
License-Expression: GPL-3.0
Classifier: Programming Language :: Python :: 3
Classifier: Programming Language :: Python :: 3.11
Classifier: Operating System :: OS Independent
Classifier: Intended Audience :: Developers
Classifier: Intended Audience :: Information Technology
Classifier: Topic :: Security
Classifier: Topic :: Software Development :: Libraries :: Python Modules
Classifier: Environment :: Console
Requires-Python: >=3.11
License-File: LICENSE
Requires-Dist: cryptography>=45.0.5
Requires-Dist: termcolor>=3.1.0
Provides-Extra: full
Requires-Dist: cryptography>=3.0.0; extra == "full"
Dynamic: license-file
